pygscholar/__init__.py
pygscholar/__main__.py
pygscholar/author.py
pygscholar/cache.py
pygscholar/cli.py
pygscholar/config.py
pygscholar/department.py
pygscholar/publication.py
pygscholar/api/__init__.py
pygscholar/api/local_db.py
pygscholar/api/scholarly.py
pygscholar/api/scraper.py
pygscholar-0.2.0.dist-info/licenses/LICENSE
pygscholar-0.2.0.dist-info/METADATA
pygscholar-0.2.0.dist-info/WHEEL
pygscholar-0.2.0.dist-info/entry_points.txt
pygscholar-0.2.0.dist-info/top_level.txt
pygscholar-0.2.0.dist-info/RECORD
