Metadata-Version: 2.4
Name: pygscholar
Version: 0.2.0
Summary: Tool for interacting with google scholar
Author-email: Henrik Finsberg <henriknf@simula.no>
License: MIT
Project-URL: Homepage, https://github.com/finsberg/pygscholar
Keywords: action potential,cell models,features
Classifier: License :: OSI Approved :: MIT License
Classifier: Programming Language :: Python :: 3
Classifier: Programming Language :: Python :: 3 :: Only
Classifier: Programming Language :: Python :: 3.7
Classifier: Programming Language :: Python :: 3.8
Classifier: Programming Language :: Python :: 3.9
Classifier: Programming Language :: Python :: 3.10
Requires-Python: >=3.8
License-File: LICENSE
Requires-Dist: pydantic
Requires-Dist: rich
Requires-Dist: scholarly
Requires-Dist: structlog
Requires-Dist: typer
Requires-Dist: selectolax
Requires-Dist: click<8.2.0
Provides-Extra: dev
Requires-Dist: bump2version; extra == "dev"
Requires-Dist: ipython; extra == "dev"
Requires-Dist: pdbpp; extra == "dev"
Requires-Dist: pre-commit; extra == "dev"
Requires-Dist: twine; extra == "dev"
Requires-Dist: wheel; extra == "dev"
Requires-Dist: ruff; extra == "dev"
Provides-Extra: docs
Requires-Dist: ipython<8.7.0; extra == "docs"
Requires-Dist: jupyter-book; extra == "docs"
Provides-Extra: slack
Requires-Dist: slack-sdk; extra == "slack"
Provides-Extra: test
Requires-Dist: pre-commit; extra == "test"
Requires-Dist: polyfactory; extra == "test"
Requires-Dist: pytest; extra == "test"
Requires-Dist: pytest-cov; extra == "test"
Requires-Dist: pytest-rerunfailures; extra == "test"
Dynamic: license-file
